luchtmeetnetapi/__init__.py
luchtmeetnetapi/api.py
luchtmeetnetapi/cache.py
luchtmeetnetapi/client.py
luchtmeetnetapi/const.py
luchtmeetnetapi/exceptions.py
luchtmeetnetapi/models.py
luchtmeetnetapi/request_client.py
luchtmeetnetapi/util.py
luchtmeetnetapi-0.1.1.dist-info/LICENSE
luchtmeetnetapi-0.1.1.dist-info/METADATA
luchtmeetnetapi-0.1.1.dist-info/WHEEL
luchtmeetnetapi-0.1.1.dist-info/RECORD
