Metadata-Version: 2.1
Name: luchtmeetnetapi
Version: 0.1.1
Summary: API client for the Dutch air quality monitoring network
Home-page: https://github.com/Daanoz/luchtmeetnetapi
License: MIT
Keywords: luchtmeetnet,api,async,client
Author: Daan Sieben
Author-email: developer@daansieben.net
Requires-Python: >=3.11,<4.0
Classifier: Development Status :: 4 - Beta
Classifier: Framework :: AsyncIO
Classifier: Intended Audience :: Developers
Classifier: License :: OSI Approved :: MIT License
Classifier: Natural Language :: English
Classifier: Programming Language :: Python :: 3
Classifier: Programming Language :: Python :: 3.11
Classifier: Programming Language :: Python :: 3.12
Classifier: Programming Language :: Python :: 3.13
Classifier: Topic :: Software Development :: Libraries :: Python Modules
Requires-Dist: aiohttp (>=3.0.0)
Requires-Dist: mashumaro (>=3.11,<4.0)
Requires-Dist: orjson (>=3.0.0)
Project-URL: Bug Tracker, https://github.com/daanoz/luchtmeetnetapi/issues
Project-URL: Changelog, https://github.com/daanoz/luchtmeetnetapi/releases
Project-URL: Documentation, https://github.com/Daanoz/luchtmeetnetapi
Project-URL: Repository, https://github.com/Daanoz/luchtmeetnetapi
